promptengine/__init__.py
promptengine/core/__init__.py
promptengine/core/prompt.py
promptengine/core/registry.py
promptengine/validation/__init__.py
promptengine/validation/validator.py
promptengine/version_control/__init__.py
promptengine/version_control/version_manager.py
sysprompt_engine-0.1.0.dist-info/licenses/LICENSE
sysprompt_engine-0.1.0.dist-info/METADATA
sysprompt_engine-0.1.0.dist-info/WHEEL
sysprompt_engine-0.1.0.dist-info/top_level.txt
sysprompt_engine-0.1.0.dist-info/RECORD
